{
  "project_info": {
    "project_number": "300912797259",
    "project_id": "whatsapp-211b9",
    "storage_bucket": "whatsapp-211b9.appspot.com"
  },
  "client": [
    {
      "client_info": {
        "mobilesdk_app_id": "1:300912797259:android:f31e2ea6c62a4cacee8fce",
        "android_client_info": {
          "package_name": "com.example.whatsapp_clone"
        }
      },
      "oauth_client": [
        {
          "client_id": "300912797259-7781oq0mjbmro6q3833kmukccqeuqu60.apps.googleusercontent.com",
          "client_type": 1,
          "android_info": {
            "package_name": "com.example.whatsapp_clone",
            "certificate_hash": "51ca73d11222010b977ac10e12e86df5527555e8"
          }
        },
        {
          "client_id": "300912797259-b1i6vk6ncdgd1bs8j3pm1cppdl9to221.apps.googleusercontent.com",
          "client_type": 3
        }
      ],
      "api_key": [
        {
          "current_key": "AIzaSyCTCg4l9pTBznvmowldSi7eLIt_Pq7LYKI"
        }
      ],
      "services": {
        "appinvite_service": {
          "other_platform_oauth_client": [
            {
              "client_id": "300912797259-b1i6vk6ncdgd1bs8j3pm1cppdl9to221.apps.googleusercontent.com",
              "client_type": 3
            }
          ]
        }
      }
    }
  ],
  "configuration_version": "1"
}